MANIFEST.in
README.md
setup.cfg
setup.py
versioneer.py
voeventdb/__init__.py
voeventdb.server.egg-info/PKG-INFO
voeventdb.server.egg-info/SOURCES.txt
voeventdb.server.egg-info/dependency_links.txt
voeventdb.server.egg-info/requires.txt
voeventdb.server.egg-info/top_level.txt
voeventdb/server/__init__.py
voeventdb/server/_version.py
voeventdb/server/bin/voeventdb_create.py
voeventdb/server/bin/voeventdb_dump_tarball.py
voeventdb/server/bin/voeventdb_ingest_packet.py
voeventdb/server/bin/voeventdb_ingest_tarball.py
voeventdb/server/database/__init__.py
voeventdb/server/database/config.py
voeventdb/server/database/convenience.py
voeventdb/server/database/db_utils.py
voeventdb/server/database/ingest.py
voeventdb/server/database/models.py
voeventdb/server/database/query.py
voeventdb/server/restapi/__init__.py
voeventdb/server/restapi/annotate.py
voeventdb/server/restapi/app.py
voeventdb/server/restapi/default_config.py
voeventdb/server/restapi/inspection_utils.py
voeventdb/server/restapi/static/css/minimalcss/minimal.css
voeventdb/server/restapi/templates/404.html
voeventdb/server/restapi/templates/errorbase.html
voeventdb/server/restapi/templates/landing.html
voeventdb/server/restapi/templates/includes/endpoints.html
voeventdb/server/restapi/v1/__init__.py
voeventdb/server/restapi/v1/apierror.py
voeventdb/server/restapi/v1/definitions.py
voeventdb/server/restapi/v1/filter_base.py
voeventdb/server/restapi/v1/filters.py
voeventdb/server/restapi/v1/jsonencoder.py
voeventdb/server/restapi/v1/viewbase.py
voeventdb/server/restapi/v1/views.py
voeventdb/server/tests/__init__.py
voeventdb/server/tests/test_fixture_creation.py
voeventdb/server/tests/fixtures/__init__.py
voeventdb/server/tests/fixtures/connection.py
voeventdb/server/tests/fixtures/fake.py
voeventdb/server/tests/fixtures/packetgen.py
voeventdb/server/tests/fixtures/testpacket_id.py
voeventdb/server/tests/resources/ASASSN#2016-09-25.47_2016fvf_PTSS-16nqb_PS16ejf.xml
voeventdb/server/tests/resources/BAT_GRB_Pos_655721-214.xml
voeventdb/server/tests/resources/Gaia16bsf.xml
voeventdb/server/tests/resources/Konus_Lightcurve_2015-07-10T00:28:01.68.xml
