Metadata-Version: 2.1
Name: voeventdb.server
Version: 1.3.4
Summary: Data-store and accompanying RESTful query API for archiving and retrieving VOEvent packets.
Home-page: https://github.com/timstaley/voeventdb
Author: Tim Staley
Author-email: github@timstaley.co.uk
License: UNKNOWN
Platform: UNKNOWN
Classifier: License :: OSI Approved :: BSD License
Classifier: Programming Language :: Python :: 2.7
Classifier: Programming Language :: Python :: 3.6
Classifier: Intended Audience :: Science/Research
Provides-Extra: all
Provides-Extra: test
